Workbook
Name BD_EESS: #REF!
Name Tabla_zonas: [1]Hoja4!$J$5:$N$111

Sheet Liquidación
A1: COTIZACIÓN DE SERVICIOS | G1: N° | H1: 56-01
B3: Servicio : | D3: N° de Solicitud: | G3: Categoria: | H3: II.EE. Baja Tensión
B4: RUC: | C4: 20539249640 | D4: Cliente: | E4: Piura - PVH | G4: CECO: | H4: =VLOOKUP(E4,'Lista de Tiendas'!A3:D200,3) -> 29150404
B5: Empresa : | C5: SAT INDUSTRIALES | D5: Jefe de Energía y SCI: | E5: Raul Quispe | G5: Fecha ejec:
B6: Cotizado Por: | C6: JOEL VIERA | D6: Fecha de cotización: | G6: Total: | H6: =+SUM(Liquidación!$H$9:$H$17) -> 0
C7: Solo digitar las columnas y celdas en celeste
A8: Item | B8: Línea | C8: Descripción de línea del preciario | D8: Comentario | E8: Unidad | F8: Cant. | G8: P.u | H8: Subtotal
A9: 1 | C9: VIATICOS
B10: VABT21 | C10: =+VLOOKUP(B10,'Preciario SAT BT'!$A$3:$D$1000,2,0) -> VIATICO CORRECTIVO DIA ADICIONAL (ALOJAMIENTO Y HOSPEDAJE) | E10: =+VLOOKUP(B10,'Preciario SAT BT'!$A$3:$D$1000,3,0) -> POR PERSONA X DIA | G10: =+VLOOKUP(B10,'Preciario SAT BT'!$A$3:$D$1000,4,0) -> 83 | H10: =+IFERROR(F10*G10,0) -> 0
C11: =+VLOOKUP(B11,'Preciario SAT BT'!$A$3:$D$1000,2,0) -> #N/A | E11: =+VLOOKUP(B11,'Preciario SAT BT'!$A$3:$D$1000,3,0) -> #N/A | G11: =+VLOOKUP(B11,'Preciario SAT BT'!$A$3:$D$1000,4,0) -> #N/A | H11: =+IFERROR(F11*G11,0) -> 0
A12: 2 | C12: SUMINISTRO
C13: =+VLOOKUP(B13,'Preciario SAT BT'!$A$3:$D$1000,2,0) -> #N/A | E13: =+VLOOKUP(B13,'Preciario SAT BT'!$A$3:$D$1000,3,0) -> #N/A | G13: =+VLOOKUP(B13,'Preciario SAT BT'!$A$3:$D$1000,4,0) -> #N/A | H13: =+IFERROR(F13*G13,0) -> 0
C14: =+VLOOKUP(B14,'Preciario SAT BT'!$A$3:$D$1000,2,0) -> #N/A | E14: =+VLOOKUP(B14,'Preciario SAT BT'!$A$3:$D$1000,3,0) -> #N/A | G14: =+VLOOKUP(B14,'Preciario SAT BT'!$A$3:$D$1000,4,0) -> #N/A | H14: =+IFERROR(F14*G14,0) -> 0
A15: 3 | C15: MANO DE OBRA
C16: =+VLOOKUP(B16,'Preciario SAT BT'!$A$3:$D$1000,2,0) -> #N/A | E16: =+VLOOKUP(B16,'Preciario SAT BT'!$A$3:$D$1000,3,0) -> #N/A | F16: 1 | G16: =+VLOOKUP(B16,'Preciario SAT BT'!$A$3:$D$1000,4,0) -> #N/A | H16: =+IFERROR(F16*G16,0) -> 0
C17: =+VLOOKUP(B17,'Preciario SAT BT'!$A$3:$D$1000,2,0) -> #N/A | E17: =+VLOOKUP(B17,'Preciario SAT BT'!$A$3:$D$1000,3,0) -> #N/A | F17: 1 | G17: =+VLOOKUP(B17,'Preciario SAT BT'!$A$3:$D$1000,4,0) -> #N/A | H17: =+IFERROR(F17*G17,0) -> 0

Sheet Preciario SAT BT
A1: PRECIARIO ADJUDICADO ENERGY: IIEE BAJA TENSIÓN
B2: Precios no incluyen IGV | C2: Esta hoja es inmodificable
A3: LÍNEA SAP | B3: DESCRIPCIÓN LINEA SAP DIAR INGENIEROS IIEE BT | C3: UNIDAD | D3: P.U.
B4: Mantenimiento Preventivo Baja Tensión
A5: MPBT01 | B5: MP TABLERO ADOSADO O EMPOTRADO | C5: UNIDAD | D5: 81.86
A6: MPBT02 | B6: MP TABLERO AUTOSOPORTADO | C6: UNIDAD | D6: 93
A7: MPBT03 | B7: MP POZO A TIERRA T_CONVENCIONAL BT | C7: UNIDAD | D7: 219.51
A8: MPBT04 | B8: MP POZO A TIERRA T_MALLA BT | C8: UNIDAD | D8: 219.51
A9: MPBT05 | B9: MP TABLERO BCO CONDENSADORES | C9: UNIDAD | D9: 221.89
A10: MPBT06 | B10: MP GENERADOR ESTATICO REACTIVOS | C10: UNIDAD | D10: 234.04
A11: MPBT07 | B11: MP FILTRO DE ARMONICOS | C11: UNIDAD | D11: 240.89
A12: MPBT08 | B12: SERV. MP VARIADORES | C12: UNIDAD | D12: 214.89
A13: MPBT09 | B13: PDR PREVENCIONISTA BT (HONORARIOS) | C13: POR VISITA / SEDE | D13: 165.76
A14: MPBT10 | B14: VIATICO DIA ADICIONAL RUTA (HOSPEDAJE Y ALIMENTACIÓN) | C14: POR RUTA X SEDE X DIA | D14: 117
A15: MPBT11 | B15: GESTION INVENTARIO ELEC TIENDA DE 0 A 10 EQUIPOS | C15: TIENDA | D15: 26.52
A16: MPBT12 | B16: GESTION INVENTARIO ELEC TIENDA DE 11 A 20 EQUIPOS | C16: TIENDA | D16: 26.52
... A25: MPBT21 | B25: GESTION INVENTARIO ELEC TIENDA DE MÁS DE 100 EQUIPOS | C25: TIENDA | D25: 41.25
A26: MPBT22 | B26: VIATICO LIMA ( CAÑETE, MALA) - ALIMENTACIÓN, HOSPEDAJE Y PASAJE I/V | C26: POR RUTA / DIA / SEDE | D26: NA
A27: MPBT23 | B27: VIATICO SUR CHICO ( ASIA) - ALIMENTACIÓN, HOSPEDAJE Y PASAJE I/V | C27: POR RUTA / DIA / SEDE | D27: NA
A28: MPBT24 | B28: VIATICO SUR ( AREQUIPA) - ALIMENTACIÓN, HOSPEDAJE Y PASAJE I/V | C28: POR RUTA / DIA / SEDE | D28: NA
A29: MPBT25 | B29: VIATICO SUR ( CUSCO) - ALIMENTACIÓN, HOSPEDAJE Y PASAJE I/V | C29: POR RUTA / DIA / SEDE | D29: NA
A30: MPBT26 | B30: VIATICO SUR ( ILO) - ALIMENTACIÓN, HOSPEDAJE Y PASAJE I/V | C30: POR RUTA / DIA / SEDE | D30: NA
A31: MPBT27 | B31: VIATICO SUR ( JULIACA) - ALIMENTACIÓN, HOSPEDAJE Y PASAJE I/V | C31: POR RUTA / DIA / SEDE | D31: NA
A32: MPBT28 | B32: VIATICO SUR ( MOQUEGUA) - ALIMENTACIÓN, HOSPEDAJE Y PASAJE I/V | C32: POR RUTA / DIA / SEDE | D32: NA
A33: MPBT29 | B33: VIATICO SUR ( PUNO) - ALIMENTACIÓN, HOSPEDAJE Y PASAJE I/V | C33: POR RUTA / DIA / SEDE | D33: NA
A34: MPBT30 | B34: VIATICO SUR ( TACNA) - ALIMENTACIÓN, HOSPEDAJE Y PASAJE I/V | C34: POR RUTA / DIA / SEDE | D34: NA
A35: MPBT31 | B35: VIATICO SUR CHICO ( CHINCHA) - ALIMENTACIÓN, HOSPEDAJE Y PASAJE I/V | C35: POR RUTA / DIA / SEDE | D35: NA
A36: MPBT32 | B36: VIATICO SUR CHICO ( ICA) - ALIMENTACIÓN, HOSPEDAJE Y PASAJE I/V | C36: POR RUTA / DIA / SEDE | D36: NA
A37: MPBT33 | B37: VIATICO SUR CHICO ( PISCO) - ALIMENTACIÓN, HOSPEDAJE Y PASAJE I/V | C37: POR RUTA / DIA / SEDE | D37: NA
A38: MPBT34 | B38: PDR PREVENCIONISTA BT (HONORARIOS) | C38: POR VISITA / SEDE | D38: 165.76
A39: MPBT35 | B39: VIATICO CENTRO ( HUANCAYO) - ALIMENTACIÓN, HOSPEDAJE Y PASAJE I/V | C39: POR RUTA X SEDE X DIA | D39: NA
A40: MPBT36 | B40: VIATICO NORTE ( CAJAMARCA) - ALIMENTACIÓN, HOSPEDAJE Y PASAJE I/V | C40: POR RUTA X SEDE X DIA | D40: 267.28
A41: MPBT37 | B41: VIATICO NORTE ( TRUJILLO) - ALIMENTACIÓN, HOSPEDAJE Y PASAJE I/V | C41: POR RUTA X SEDE X DIA | D41: 190
A42: MPBT38 | B42: VIATICO NORTE ( CHICLAYO) - ALIMENTACIÓN, HOSPEDAJE Y PASAJE I/V | C42: POR RUTA X SEDE X DIA | D42: 177.83
A43: MPBT39 | B43: VIATICO NORTE ( CHIMBOTE) - ALIMENTACIÓN, HOSPEDAJE Y PASAJE I/V | C43: POR RUTA X SEDE X DIA | D43: 202
A44: MPBT40 | B44: VIATICO NORTE ( PIURA) - ALIMENTACIÓN, HOSPEDAJE Y PASAJE I/V | C44: POR RUTA X SEDE X DIA | D44: 29
A45: MPBT41 | B45: VIATICO NORTE ( JAÉN) - ALIMENTACIÓN, HOSPEDAJE Y PASAJE I/V | C45: POR RUTA X SEDE X DIA | D45: 206.37
A46: MPBT42 | B46: VIATICO NORTE ( PAITA) - ALIMENTACIÓN, HOSPEDAJE Y PASAJE I/V | C46: POR RUTA X SEDE X DIA | D46: 34
A47: MPBT43 | B47: VIATICO NORTE ( SULLANA) - ALIMENTACIÓN, HOSPEDAJE Y PASAJE I/V | C47: POR RUTA X SEDE X DIA | D47: 34
A48: MPBT44 | B48: VIATICO NORTE ( TALARA) - ALIMENTACIÓN, HOSPEDAJE Y PASAJE I/V | C48: POR RUTA X SEDE X DIA | D48: 48
A49: MPBT45 | B49: VIATICO NORTE ( TUMBES) - ALIMENTACIÓN, HOSPEDAJE Y PASAJE I/V | C49: POR RUTA X SEDE X DIA | D49: 140
A50: MPBT46 | B50: VIATICO NORTE CHICO ( BARRANCA) - ALIMENTACIÓN, HOSPEDAJE Y PASAJE I/V | C50: POR RUTA X SEDE X DIA | D50: NA
A51: MPBT47 | B51: VIATICO NORTE CHICO ( HUACHO) - ALIMENTACIÓN, HOSPEDAJE Y PASAJE I/V | C51: POR RUTA X SEDE X DIA | D51: NA
A52: MPBT48 | B52: VIATICO NORTE CHICO ( HUARAL) - ALIMENTACIÓN, HOSPEDAJE Y PASAJE I/V | C52: POR RUTA X SEDE X DIA | D52: NA
A53: MPBT49 | B53: VIATICO ORIENTE ( HUÁNUCO) - ALIMENTACIÓN, HOSPEDAJE Y PASAJE I/V | C53: POR RUTA X SEDE X DIA | D53: NA
A54: MPBT50 | B54: VIATICO ORIENTE ( PUCALLPA) - ALIMENTACIÓN, HOSPEDAJE Y PASAJE I/V | C54: POR RUTA X SEDE X DIA | D54: NA
A55: MPBT51 | B55: VIATICO ORIENTE ( TARAPOTO) - ALIMENTACIÓN, HOSPEDAJE Y PASAJE I/V | C55: POR RUTA X SEDE X DIA | D55: NA
A56: MPBT52 | B56: LIMPIEZA DE PANTALLA Y/O DIFUSOR DE LUMINARIA EN EXTERIORES MAX 15M (POSTES, PAREDES, ETC, INCLUYE TODAS LAS FACILIDADES QUE SE REQUIERAN PARA EJECUTAR EL TRABAJO EN ALTURA). | C56: DE 1 A 20 UNIDADES
A57: MPBT53 | B57: LIMPIEZA DE PANTALLA Y/O DIFUSOR DE LUMINARIA EN EXTERIORES MAX 15M (POSTES, PAREDES, ETC, INCLUYE TODAS LAS FACILIDADES QUE SE REQUIERAN PARA EJECUTAR EL TRABAJO EN ALTURA). | C57: DE 21 A 50 UNIDADES
A58: MPBT54 | B58: LIMPIEZA DE PANTALLA Y/O DIFUSOR DE LUMINARIA EN EXTERIORES MAX 15M (POSTES, PAREDES, ETC, INCLUYE TODAS LAS FACILIDADES QUE SE REQUIERAN PARA EJECUTAR EL TRABAJO EN ALTURA). | C58: DE 51 A 70 UNIDADES
A59: MPBT55 | B59: LIMPIEZA DE PANTALLA Y/O DIFUSOR DE LUMINARIA EN EXTERIORES MAX 15M (POSTES, PAREDES, ETC, INCLUYE TODAS LAS FACILIDADES QUE SE REQUIERAN PARA EJECUTAR EL TRABAJO EN ALTURA). | C59: DE 71 A MÁS UNIDADES
A60: MPBT56 | B60: LIMPIEZA DE PANTALLA Y/O DIFUSOR DE LUMINARIA EN SALA DE VENTAS MAX. 5M (INCLUYE TODAS LAS FACILIDADES QUE SE REQUIERAN PARA EJECUTAR EL TRABAJO EN ALTURA). | C60: DE 1 A 20 UNIDADES
A61: MPBT57 | B61: LIMPIEZA DE PANTALLA Y/O DIFUSOR DE LUMINARIA EN SALA DE VENTAS MAX. 5M (INCLUYE TODAS LAS FACILIDADES QUE SE REQUIERAN PARA EJECUTAR EL TRABAJO EN ALTURA). | C61: DE 21 A 50 UNIDADES
A62: MPBT58 | B62: LIMPIEZA DE PANTALLA Y/O DIFUSOR DE LUMINARIA EN SALA DE VENTAS MAX. 5M (INCLUYE TODAS LAS FACILIDADES QUE SE REQUIERAN PARA EJECUTAR EL TRABAJO EN ALTURA). | C62: DE 51 A 70 UNIDADES
A63: MPBT59 | B63: LIMPIEZA DE PANTALLA Y/O DIFUSOR DE LUMINARIA EN SALA DE VENTAS MAX. 5M (INCLUYE TODAS LAS FACILIDADES QUE SE REQUIERAN PARA EJECUTAR EL TRABAJO EN ALTURA). | C63: DE 71 A MÁS UNIDADES
A64: MPBT60 | B64: LIMPIEZA DE PANTALLA Y/O DIFUSOR DE LUMINARIA EN TRANSTIENDA MAX. 3.5M (OFICINAS, ALMACENES, SSHH, PLAYA ESTACIONAMIENTO, ETC, INCLUYE TODAS LAS FACILIDADES QUE SE REQUIERAN PARA EJECUTAR EL TRABAJO EN ALTURA). | C64: DE 1 A 20 UNIDADES
A65: MPBT61 | B65: LIMPIEZA DE PANTALLA Y/O DIFUSOR DE LUMINARIA EN TRANSTIENDA MAX. 3.5M (OFICINAS, ALMACENES, SSHH, PLAYA ESTACIONAMIENTO, ETC, INCLUYE TODAS LAS FACILIDADES QUE SE REQUIERAN PARA EJECUTAR EL TRABAJO EN ALTURA). | C65: DE 21 A 50 UNIDADES
A66: MPBT62 | B66: LIMPIEZA DE PANTALLA Y/O DIFUSOR DE LUMINARIA EN TRANSTIENDA MAX. 3.5M (OFICINAS, ALMACENES, SSHH, PLAYA ESTACIONAMIENTO, ETC, INCLUYE TODAS LAS FACILIDADES QUE SE REQUIERAN PARA EJECUTAR EL TRABAJO EN ALTURA). | C66: DE 51 A 70 UNIDADES
A67: MPBT63 | B67: LIMPIEZA DE PANTALLA Y/O DIFUSOR DE LUMINARIA EN TRANSTIENDA MAX. 3.5M (OFICINAS, ALMACENES, SSHH, PLAYA ESTACIONAMIENTO, ETC, INCLUYE TODAS LAS FACILIDADES QUE SE REQUIERAN PARA EJECUTAR EL TRABAJO EN ALTURA). | C67: DE 71 A MÁS UNIDADES
... A71: MPBT67 | B71: LIMPIEZA DE PANTALLA Y/O DIFUSOR DE LUMINARIA EN TRANSTIENDA MAX. 5M (OFICINAS, ALMACENES, SSHH, PLAYA ESTACIONAMIENTO, ETC, INCLUYE TODAS LAS FACILIDADES QUE SE REQUIERAN PARA EJECUTAR EL TRABAJO EN ALTURA). | C71: DE 71 A MÁS UNIDADES
B72: Mantenimiento Correctivos Baja Tensión
A73: MCBT01 | B73: ASISTENCIA TÉCNICA PARA EMERGENCIAS (SERVICIO PROFESIONAL PARA DIAGNÓSTICO Y SOLUCIONES PARCIALES INCLUYE LAS DERIVADAS DE VISITAS INDECI, OSINERGMIN Y DEFENSA CIVI, DEBE CONTEMPLAR CONSUMIBLES MENORES). | C73: UNIDAD | D73: 324.18
A74: MCBT02 | B74: ASISTENCIA TÉCNICA PARA EMERGENCIAS (SERVICIO PROFESIONAL PARA DIAGNÓSTICO Y SOLUCIONES PARCIALES INCLUYE LAS DERIVADAS DE VISITAS INDECI, OSINERGMIN Y DEFENSA CIVI, DEBE CONTEMPLAR CONSUMIBLES MENORES). | C74: DE 1 A 10 EVENTO / MES | D74: 324.18
A75: MCBT03 | B75: ASISTENCIA TÉCNICA PARA EMERGENCIAS (SERVICIO PROFESIONAL PARA DIAGNÓSTICO Y SOLUCIONES PARCIALES INCLUYE LAS DERIVADAS DE VISITAS INDECI, OSINERGMIN Y DEFENSA CIVI, DEBE CONTEMPLAR CONSUMIBLES MENORES). | C75: DE 11 A 20 EVENTOS/ MES | D75: 324.18
A76: MCBT04 | B76: ASISTENCIA TÉCNICA PARA EMERGENCIAS (SERVICIO PROFESIONAL PARA DIAGNÓSTICO Y SOLUCIONES PARCIALES INCLUYE LAS DERIVADAS DE VISITAS INDECI, OSINERGMIN Y DEFENSA CIVI, DEBE CONTEMPLAR CONSUMIBLES MENORES). | C76: DE 21 A 40 EVENTOS/ MES | D76: 324.18
A77: MCBT05 | B77: ACONDICIONAMIENTO DE TABLERO ELÉCTRICO (INCLUYE EL ORDENAMIENDO Y PEINADO DE TODOS LOS CABLES, MONTAJE Y/O AJUSTE DE TODOS LAS CONEXIONES EN LOS INTERRUPTORES, CINTILLOS, CINTA ESPIRAL, OTROS). | C77: UNIDAD | D77: 196
A78: MCBT06 | B78: ACTUALIZACIÓN DE DIAGRAMA UNIFILAR DIGITAL SEGÚN ESTANDAR (ESTA LÍNEA SOLO APLICA PARA CASOS QUE ESTÉN FUERA DEL MANTENIMIENTO PREVENTIVO Y LAS OBSERVACIONES QUE DERIVEN DE ELLA) | C78: UNIDAD | D78: 32
A79: MCBT07 | B79: ADOSAMIENTO DE TABLERO ELÉCTRICO (INCLUYE MATERIALES DE FIJACIÓN: PERNOS, ARANDELAS, OTROS). | C79: UNIDAD | D79: 93
A80: MCBT08 | B80: ANÁLISIS FÍSICO QUÍMICO DE ACEITE DE TRANSFORMADOR (ESTÁ LÍNEA NO APLICA PARA LOS MANTENIMIENTOS PREVENTIVOS ) | C80: UNIDAD | D80: 463.25
A81: MCBT09 | B81: ANULACIÓN DE CIRCUITO ELÉCTRICO (INCLUYE DESCONEXIÓN Y RETIRO DE CABLES Y/O ITM. ESTA LÍNEA SE USARÁ EXCLUSIVAMENTE CUANDO SE SOLICITE LA ANULACIÓN DE UN CIRCUITO POR EL RETIRO DE UNA CARGA O BAJA DE ALGÚN ACTIVO. | C81: UNIDAD | D81: 204
A82: MCBT10 | B82: ATERRAMIENTO DE EQUIPOS ELECTRICOS (GRUPOS ELECTRÓGENOS) INCLUYE CABLE (MÁXIMO 1ML), TERMINALES Y ACCESORIOS DE SUJECCIÓN PARA CULMINAR EL TRABAJO | C82: UNIDAD | D82: 16.4
A83: MCBT11 | B83: ATERRAMIENTO DE EQUIPOS ELECTRICOS (HVA, EXTRACTORES, VENTILADORES, BOMBAS,ETC) INCLUYE CABLE (MÁXIMO 1ML), TERMINALES Y ACCESORIOS DE SUJECCIÓN PARA CULMINAR EL TRABAJO | C83: UNIDAD | D83: 16.4
A84: MCBT12 | B84: ATERRAMIENTO DE TABLEROS ELECTRICOS INCLUYE CABLE (MÁXIMO 1ML), TERMINALES Y ACCESORIOS DE SUJECCIÓN PARA CULMINAR EL TRABAJO | C84: UNIDAD | D84: 16.4
... A665: MCBT593 | B665: Repuestos auxiliares NO reccurrentes IIEE BAJA TENSIÓN | C665: UNIDAD | D665: 1
B666: Viaticos correctivos Baja Tensión
A667: VTBT01 | B667: VIATICO CORRECTIVO LIMA ( CAÑETE, MALA) - ALIMENTACIÓN, HOSPEDAJE Y PASAJE I/V TERRESTRE | C667: POR PERSONA | D667: NA
A668: VTBT02 | B668: VIATICO CORRECTIVO SUR CHICO ( ASIA) - ALIMENTACIÓN, HOSPEDAJE Y PASAJE I/V TERRESTRE | C668: POR PERSONA | D668: NA
A669: VTBT03 | B669: VIATICO CORRECTIVO CENTRO ( HUANCAYO) - ALIMENTACIÓN, HOSPEDAJE Y PASAJE I/V TERRESTRE | C669: POR PERSONA | D669: NA
A670: VTBT04 | B670: VIATICO CORRECTIVO NORTE ( CAJAMARCA) - ALIMENTACIÓN, HOSPEDAJE Y PASAJE I/V TERRESTRE | C670: POR PERSONA | D670: 261
A671: VTBT05 | B671: VIATICO CORRECTIVO NORTE ( TRUJILLO) - ALIMENTACIÓN, HOSPEDAJE Y PASAJE I/V TERRESTRE | C671: POR PERSONA | D671: 190
A672: VTBT06 | B672: VIATICO CORRECTIVO NORTE ( CHICLAYO) - ALIMENTACIÓN, HOSPEDAJE Y PASAJE I/V TERRESTRE | C672: POR PERSONA | D672: 177.83
A673: VTBT07 | B673: VIATICO CORRECTIVO NORTE ( CHIMBOTE) - ALIMENTACIÓN, HOSPEDAJE Y PASAJE I/V TERRESTRE | C673: POR PERSONA | D673: 202
A674: VTBT08 | B674: VIATICO CORRECTIVO NORTE ( PIURA) - ALIMENTACIÓN, HOSPEDAJE Y PASAJE I/V TERRESTRE | C674: POR PERSONA | D674: 165
A675: VTBT09 | B675: VIATICO CORRECTIVO NORTE ( JAÉN) - ALIMENTACIÓN, HOSPEDAJE Y PASAJE I/V TERRESTRE | C675: POR PERSONA | D675: 206.37
A676: VTBT10 | B676: VIATICO CORRECTIVO NORTE ( PAITA) - ALIMENTACIÓN, HOSPEDAJE Y PASAJE I/V TERRESTRE | C676: POR PERSONA | D676: 165
A677: VTBT11 | B677: VIATICO CORRECTIVO NORTE ( SULLANA) - ALIMENTACIÓN, HOSPEDAJE Y PASAJE I/V TERRESTRE | C677: POR PERSONA | D677: 165
A678: VTBT12 | B678: VIATICO CORRECTIVO NORTE ( TALARA) - ALIMENTACIÓN, HOSPEDAJE Y PASAJE I/V TERRESTRE | C678: POR PERSONA | D678: 270
A679: VTBT13 | B679: VIATICO CORRECTIVO NORTE ( TUMBES) - ALIMENTACIÓN, HOSPEDAJE Y PASAJE I/V TERRESTRE | C679: POR PERSONA | D679: 233.28
A680: VTBT14 | B680: VIATICO CORRECTIVO NORTE CHICO ( BARRANCA) - ALIMENTACIÓN, HOSPEDAJE Y PASAJE I/V TERRESTRE | C680: POR PERSONA | D680: NA
A681: VTBT15 | B681: VIATICO CORRECTIVO NORTE CHICO ( HUACHO) - ALIMENTACIÓN, HOSPEDAJE Y PASAJE I/V TERRESTRE | C681: POR PERSONA | D681: NA
A682: VTBT16 | B682: VIATICO CORRECTIVO NORTE CHICO ( HUARAL) - ALIMENTACIÓN, HOSPEDAJE Y PASAJE I/V TERRESTRE | C682: POR PERSONA | D682: NA
A683: VTBT17 | B683: VIATICO CORRECTIVO ORIENTE ( HUÁNUCO) - ALIMENTACIÓN, HOSPEDAJE Y PASAJE I/V TERRESTRE | C683: POR PERSONA | D683: NA
A684: VTBT18 | B684: VIATICO CORRECTIVO ORIENTE ( PUCALLPA) - ALIMENTACIÓN, HOSPEDAJE Y PASAJE I/V TERRESTRE | C684: POR PERSONA | D684: NA
A685: VTBT19 | B685: VIATICO CORRECTIVO ORIENTE ( TARAPOTO) - ALIMENTACIÓN, HOSPEDAJE Y PASAJE I/V TERRESTRE | C685: POR PERSONA | D685: NA
A686: VTBT20 | B686: VIATICO CORRECTIVO SUR ( AREQUIPA) - ALIMENTACIÓN, HOSPEDAJE Y PASAJE I/V TERRESTRE | C686: POR PERSONA | D686: NA
A687: VTBT21 | B687: VIATICO CORRECTIVO SUR ( CUSCO) - ALIMENTACIÓN, HOSPEDAJE Y PASAJE I/V TERRESTRE | C687: POR PERSONA | D687: NA
A688: VTBT22 | B688: VIATICO CORRECTIVO SUR ( ILO) - ALIMENTACIÓN, HOSPEDAJE Y PASAJE I/V TERRESTRE | C688: POR PERSONA | D688: NA
A689: VTBT23 | B689: VIATICO CORRECTIVO SUR ( JULIACA) - ALIMENTACIÓN, HOSPEDAJE Y PASAJE I/V TERRESTRE | C689: POR PERSONA | D689: NA
A690: VTBT24 | B690: VIATICO CORRECTIVO SUR ( MOQUEGUA) - ALIMENTACIÓN, HOSPEDAJE Y PASAJE I/V TERRESTRE | C690: POR PERSONA | D690: NA
A691: VTBT25 | B691: VIATICO CORRECTIVO SUR ( PUNO) - ALIMENTACIÓN, HOSPEDAJE Y PASAJE I/V TERRESTRE | C691: POR PERSONA | D691: NA
...

Sheet Lista de Tiendas
A2: TIENDA | B2: FORMATO | C2: CECO | D2: SOCIEDAD | G2: RUBRO | L2: FORMATO
A3: Jockey Plaza - PVH | B3: PVH | C3: 25102001 | D3: A125 | G3: Grupos electrógenos | L3: PVH
A4: Higuereta - PVH | B4: PVH | C4: 25102002 | D4: A125 | G4: II.EE. Baja Tensión | L4: PVO
A5: Brasil - PVH | B5: PVH | C5: 25102004 | D5: A125 | G5: II.EE. Media Tensión | L5: PVS
A6: Cortijo - PVH | B6: PVH | C6: 25102005 | D6: A125 | G6: UPS | L6: PVE
A7: Callao - PVH | B7: PVH | C7: 25102006 | D7: A125 | G7: Sistema Contraincendios | L7: VV
A8: Ate - PVH | B8: PVH | C8: 25102008 | D8: A125 | G8: Extintores | L8: MK
A9: Bolichera - PVH | B9: PVH | C9: 25102009 | D9: A125 | G9: Puertas cortafuegos | L9: JKR
A10: Risso - PVH | B10: PVH | C10: 25102011 | D10: A125 | L10: ALM.
A11: Los Olivos - PVH | B11: PVH | C11: 25102013 | D11: A125 | L11: OFIC.
A12: Comas - PVH | B12: PVH | C12: 25102014 | D12: A125
A13: Trujillo - PVH | B13: PVH | C13: 25102017 | D13: A125
A14: Chiclayo - PVH | B14: PVH | C14: 25102018 | D14: A125
A15: Arequipa - PVH | B15: PVH | C15: 25102019 | D15: A125
A16: Ceres - PVH | B16: PVH | C16: 25102020 | D16: A125
A17: Pro - PVH | B17: PVH | C17: 25102021 | D17: A125
A18: Huancayo - PVH | B18: PVH | C18: 25102022 | D18: A125
A19: Izaguirre - PVH | B19: PVH | C19: 25102023 | D19: A125
A20: Alfonso Ugarte - PVH | B20: PVH | C20: 25102024 | D20: A125
A21: Universitaria - PVH | B21: PVH | C21: 25102025 | D21: A125
A22: Puente Piedra - PVH | B22: PVH | C22: 25102026 | D22: A125
A23: SJ Lurigancho - PVH | B23: PVH | C23: 25102030 | D23: A125
... A148: SMP - MK | B148: MK | C148: 24107042 | D148: A124
A149: SJM - MK | B149: MK | D149: A124
A150: HO (Oficina Central) - MK
A151: Cusco - MK (Centro Comercial)
A154: HUB 001 Miraflores | B154: JKR | D154: A128
A155: HUB 002 Surco / Jorge Chavez | B155: JKR | D155: A128
A156: HUB 004 Lince | B156: JKR | D156: A128
A157: HUB 005 Surco / Benavides | B157: JKR | D157: A128
A158: HUB 006 Pueblo Libre | B158: JKR | D158: A128
A159: HUB 007 Surco / Primavera | B159: JKR | D159: A128
A160: HUB 009 San Luis | B160: JKR | D160: A128
A161: HUB 011 Punta Hermosa | B161: JKR | D161: A128
A162: HUB 013 Surquillo | B162: JKR | D162: A128
A165: Alm. Santa Rosa | B165: ALM. | C165: 29150404
A166: Oficinas Morelli | B166: OFIC. | C166: 29150404 | D166: A129

Sheet Inf. Cierre SAP C.M
B2: INFORME DE CIERRE CONTABLE COORDINADOR DE MANTENIMIENTO
G3: =SUM('Inf. Cierre SAP C.M'!$G$5:$G$29) -> 0
B4: N° Orden Mantto | C4: N° Solicitud | D4: N° Solped | E4: N° Pedido | F4: N° MIGO | G4: Subtotal S/.
